// Class: io/quarkus/runner/ApplicationImpl1
//     Access =  public synthetic
//     Extends: io/quarkus/runtime/Application

// DO NOT MODIFY.  This is not actually a source file; it is a textual representation of generated code.
// Use only for debugging purposes.

// Auto-generated constructor
// Access: public
Method <init> : V
(
    // (no arguments)
) {
    ALOAD 0
    // Method descriptor: ()V
    INVOKESPECIAL io/quarkus/runtime/Application#<init>
    RETURN
    
}

// Access: static
Field STARTUP_CONTEXT : Lio/quarkus/runtime/StartupContext;

// Access: protected final
Method doStart : V
(
    arg 1 = [Ljava/lang/String;
) {
    ** label1
    LDC (String) "java.util.logging.manager"
    LDC (String) "org.jboss.logmanager.LogManager"
    // Method descriptor: (Ljava/lang/String;Ljava/lang/String;)Ljava/lang/String;
    INVOKESTATIC java/lang/System#setProperty
    POP
    LDC (String) "io.netty.allocator.maxOrder"
    LDC (String) "1"
    // Method descriptor: (Ljava/lang/String;Ljava/lang/String;)Ljava/lang/String;
    INVOKESTATIC java/lang/System#setProperty
    POP
    // Method descriptor: ()V
    INVOKESTATIC io/quarkus/runtime/SubstrateRuntimePropertiesRecorder#doRuntime
    // Method descriptor: ()V
    INVOKESTATIC io/quarkus/runtime/Timing#mainStarted
    // Field descriptor: Lio/quarkus/runtime/StartupContext;
    GETSTATIC io/quarkus/runner/ApplicationImpl1#STARTUP_CONTEXT
    ASTORE 2
    ** label2
    // Method descriptor: ()V
    INVOKESTATIC io/quarkus/runtime/generated/RunTimeConfig#getRunTimeConfiguration
    NEW io/quarkus/deployment/steps/AgroalProcessor$configureRuntimeProperties7
    DUP
    // Method descriptor: ()V
    INVOKESPECIAL io/quarkus/deployment/steps/AgroalProcessor$configureRuntimeProperties7#<init>
    CHECKCAST io/quarkus/runtime/StartupTask
    ALOAD 2
    // Method descriptor: (Lio/quarkus/runtime/StartupContext;)V
    INVOKEINTERFACE io/quarkus/runtime/StartupTask#deploy
    NEW io/quarkus/deployment/steps/LoggingResourceProcessor$setupLoggingRuntimeInit10
    DUP
    // Method descriptor: ()V
    INVOKESPECIAL io/quarkus/deployment/steps/LoggingResourceProcessor$setupLoggingRuntimeInit10#<init>
    CHECKCAST io/quarkus/runtime/StartupTask
    ALOAD 2
    // Method descriptor: (Lio/quarkus/runtime/StartupContext;)V
    INVOKEINTERFACE io/quarkus/runtime/StartupTask#deploy
    NEW io/quarkus/deployment/steps/VertxHttpProcessor$cors11
    DUP
    // Method descriptor: ()V
    INVOKESPECIAL io/quarkus/deployment/steps/VertxHttpProcessor$cors11#<init>
    CHECKCAST io/quarkus/runtime/StartupTask
    ALOAD 2
    // Method descriptor: (Lio/quarkus/runtime/StartupContext;)V
    INVOKEINTERFACE io/quarkus/runtime/StartupTask#deploy
    NEW io/quarkus/deployment/steps/VertxWebProcessor$bodyHandler12
    DUP
    // Method descriptor: ()V
    INVOKESPECIAL io/quarkus/deployment/steps/VertxWebProcessor$bodyHandler12#<init>
    CHECKCAST io/quarkus/runtime/StartupTask
    ALOAD 2
    // Method descriptor: (Lio/quarkus/runtime/StartupContext;)V
    INVOKEINTERFACE io/quarkus/runtime/StartupTask#deploy
    NEW io/quarkus/deployment/steps/NettyProcessor$eagerlyInitClass2
    DUP
    // Method descriptor: ()V
    INVOKESPECIAL io/quarkus/deployment/steps/NettyProcessor$eagerlyInitClass2#<init>
    CHECKCAST io/quarkus/runtime/StartupTask
    ALOAD 2
    // Method descriptor: (Lio/quarkus/runtime/StartupContext;)V
    INVOKEINTERFACE io/quarkus/runtime/StartupTask#deploy
    NEW io/quarkus/deployment/steps/VertxCoreProcessor$eventLoopCount4
    DUP
    // Method descriptor: ()V
    INVOKESPECIAL io/quarkus/deployment/steps/VertxCoreProcessor$eventLoopCount4#<init>
    CHECKCAST io/quarkus/runtime/StartupTask
    ALOAD 2
    // Method descriptor: (Lio/quarkus/runtime/StartupContext;)V
    INVOKEINTERFACE io/quarkus/runtime/StartupTask#deploy
    NEW io/quarkus/deployment/steps/VertxCoreProcessor$buildWeb9
    DUP
    // Method descriptor: ()V
    INVOKESPECIAL io/quarkus/deployment/steps/VertxCoreProcessor$buildWeb9#<init>
    CHECKCAST io/quarkus/runtime/StartupTask
    ALOAD 2
    // Method descriptor: (Lio/quarkus/runtime/StartupContext;)V
    INVOKEINTERFACE io/quarkus/runtime/StartupTask#deploy
    NEW io/quarkus/deployment/steps/ThreadPoolSetup$createExecutor8
    DUP
    // Method descriptor: ()V
    INVOKESPECIAL io/quarkus/deployment/steps/ThreadPoolSetup$createExecutor8#<init>
    CHECKCAST io/quarkus/runtime/StartupTask
    ALOAD 2
    // Method descriptor: (Lio/quarkus/runtime/StartupContext;)V
    INVOKEINTERFACE io/quarkus/runtime/StartupTask#deploy
    NEW io/quarkus/deployment/steps/NarayanaJtaProcessor$build3
    DUP
    // Method descriptor: ()V
    INVOKESPECIAL io/quarkus/deployment/steps/NarayanaJtaProcessor$build3#<init>
    CHECKCAST io/quarkus/runtime/StartupTask
    ALOAD 2
    // Method descriptor: (Lio/quarkus/runtime/StartupContext;)V
    INVOKEINTERFACE io/quarkus/runtime/StartupTask#deploy
    NEW io/quarkus/deployment/steps/ConfigBuildStep$validateConfigProperties24
    DUP
    // Method descriptor: ()V
    INVOKESPECIAL io/quarkus/deployment/steps/ConfigBuildStep$validateConfigProperties24#<init>
    CHECKCAST io/quarkus/runtime/StartupTask
    ALOAD 2
    // Method descriptor: (Lio/quarkus/runtime/StartupContext;)V
    INVOKEINTERFACE io/quarkus/runtime/StartupTask#deploy
    NEW io/quarkus/deployment/steps/HibernateOrmProcessor$startPersistenceUnits28
    DUP
    // Method descriptor: ()V
    INVOKESPECIAL io/quarkus/deployment/steps/HibernateOrmProcessor$startPersistenceUnits28#<init>
    CHECKCAST io/quarkus/runtime/StartupTask
    ALOAD 2
    // Method descriptor: (Lio/quarkus/runtime/StartupContext;)V
    INVOKEINTERFACE io/quarkus/runtime/StartupTask#deploy
    NEW io/quarkus/deployment/steps/VertxCoreProcessor$build26
    DUP
    // Method descriptor: ()V
    INVOKESPECIAL io/quarkus/deployment/steps/VertxCoreProcessor$build26#<init>
    CHECKCAST io/quarkus/runtime/StartupTask
    ALOAD 2
    // Method descriptor: (Lio/quarkus/runtime/StartupContext;)V
    INVOKEINTERFACE io/quarkus/runtime/StartupTask#deploy
    NEW io/quarkus/deployment/steps/VertxProcessor$build30
    DUP
    // Method descriptor: ()V
    INVOKESPECIAL io/quarkus/deployment/steps/VertxProcessor$build30#<init>
    CHECKCAST io/quarkus/runtime/StartupTask
    ALOAD 2
    // Method descriptor: (Lio/quarkus/runtime/StartupContext;)V
    INVOKEINTERFACE io/quarkus/runtime/StartupTask#deploy
    NEW io/quarkus/deployment/steps/UndertowBuildStep$boot33
    DUP
    // Method descriptor: ()V
    INVOKESPECIAL io/quarkus/deployment/steps/UndertowBuildStep$boot33#<init>
    CHECKCAST io/quarkus/runtime/StartupTask
    ALOAD 2
    // Method descriptor: (Lio/quarkus/runtime/StartupContext;)V
    INVOKEINTERFACE io/quarkus/runtime/StartupTask#deploy
    NEW io/quarkus/deployment/steps/VertxHttpProcessor$initializeRouter34
    DUP
    // Method descriptor: ()V
    INVOKESPECIAL io/quarkus/deployment/steps/VertxHttpProcessor$initializeRouter34#<init>
    CHECKCAST io/quarkus/runtime/StartupTask
    ALOAD 2
    // Method descriptor: (Lio/quarkus/runtime/StartupContext;)V
    INVOKEINTERFACE io/quarkus/runtime/StartupTask#deploy
    NEW io/quarkus/deployment/steps/VertxHttpProcessor$finalizeRouter35
    DUP
    // Method descriptor: ()V
    INVOKESPECIAL io/quarkus/deployment/steps/VertxHttpProcessor$finalizeRouter35#<init>
    CHECKCAST io/quarkus/runtime/StartupTask
    ALOAD 2
    // Method descriptor: (Lio/quarkus/runtime/StartupContext;)V
    INVOKEINTERFACE io/quarkus/runtime/StartupTask#deploy
    NEW io/quarkus/deployment/steps/LifecycleEventsBuildStep$startupEvent36
    DUP
    // Method descriptor: ()V
    INVOKESPECIAL io/quarkus/deployment/steps/LifecycleEventsBuildStep$startupEvent36#<init>
    CHECKCAST io/quarkus/runtime/StartupTask
    ALOAD 2
    // Method descriptor: (Lio/quarkus/runtime/StartupContext;)V
    INVOKEINTERFACE io/quarkus/runtime/StartupTask#deploy
    LDC (String) "auditing-vegetables-service"
    LDC (String) "1.0-SNAPSHOT"
    LDC (String) "0.25.0"
    LDC (String) "agroal, cdi, hibernate-orm, jdbc-postgresql, narayana-jta, resteasy, resteasy-jsonb, security, servlet, smallrye-jwt, vertx, vertx-web"
    LDC (String) "prod"
    LDC (Boolean) false
    // Method descriptor: (Ljava/lang/String;Ljava/lang/String;Ljava/lang/String;Ljava/lang/String;Ljava/lang/String;Z)V
    INVOKESTATIC io/quarkus/runtime/Timing#printStartupTime
    ** label3
    GOTO label4
    ** label5
    ASTORE 3
    ALOAD 3
    // Method descriptor: ()V
    INVOKEVIRTUAL java/lang/Throwable#printStackTrace
    ALOAD 2
    // Method descriptor: ()V
    INVOKEVIRTUAL io/quarkus/runtime/StartupContext#close
    NEW java/lang/RuntimeException
    DUP
    LDC (String) "Failed to start quarkus"
    ALOAD 3
    // Method descriptor: (Ljava/lang/String;Ljava/lang/Throwable;)V
    INVOKESPECIAL java/lang/RuntimeException#<init>
    CHECKCAST java/lang/Throwable
    ATHROW
    ** label6
    GOTO label4
    // Try from label2 to label3
    // Catch java/lang/Throwable by going to label5
    ** label4
    RETURN
    ** label7
    
}

// Access: protected final
Method doStop : V
(
    // (no arguments)
) {
    ** label1
    // Field descriptor: Lio/quarkus/runtime/StartupContext;
    GETSTATIC io/quarkus/runner/ApplicationImpl1#STARTUP_CONTEXT
    // Method descriptor: ()V
    INVOKEVIRTUAL io/quarkus/runtime/StartupContext#close
    RETURN
    ** label2
    
}

// Access: public static
Method <clinit> : V
(
    // (no arguments)
) {
    ** label1
    LDC (String) "java.util.logging.manager"
    LDC (String) "org.jboss.logmanager.LogManager"
    // Method descriptor: (Ljava/lang/String;Ljava/lang/String;)Ljava/lang/String;
    INVOKESTATIC java/lang/System#setProperty
    POP
    LDC (String) "io.netty.allocator.maxOrder"
    LDC (String) "1"
    // Method descriptor: (Ljava/lang/String;Ljava/lang/String;)Ljava/lang/String;
    INVOKESTATIC java/lang/System#setProperty
    POP
    // Method descriptor: ()V
    INVOKESTATIC io/quarkus/runtime/Timing#staticInitStarted
    NEW io/quarkus/runtime/StartupContext
    DUP
    // Method descriptor: ()V
    INVOKESPECIAL io/quarkus/runtime/StartupContext#<init>
    ASTORE 0
    ALOAD 0
    // Field descriptor: Lio/quarkus/runtime/StartupContext;
    PUTSTATIC io/quarkus/runner/ApplicationImpl1#STARTUP_CONTEXT
    ** label2
    NEW io/quarkus/deployment/steps/LoggingResourceProcessor$setupLoggingStaticInit1
    DUP
    // Method descriptor: ()V
    INVOKESPECIAL io/quarkus/deployment/steps/LoggingResourceProcessor$setupLoggingStaticInit1#<init>
    CHECKCAST io/quarkus/runtime/StartupTask
    ALOAD 0
    // Method descriptor: (Lio/quarkus/runtime/StartupContext;)V
    INVOKEINTERFACE io/quarkus/runtime/StartupTask#deploy
    NEW io/quarkus/deployment/steps/VertxCoreProcessor$ioThreadDetector5
    DUP
    // Method descriptor: ()V
    INVOKESPECIAL io/quarkus/deployment/steps/VertxCoreProcessor$ioThreadDetector5#<init>
    CHECKCAST io/quarkus/runtime/StartupTask
    ALOAD 0
    // Method descriptor: (Lio/quarkus/runtime/StartupContext;)V
    INVOKEINTERFACE io/quarkus/runtime/StartupTask#deploy
    NEW io/quarkus/deployment/steps/BlockingOperationControlBuildStep$blockingOP15
    DUP
    // Method descriptor: ()V
    INVOKESPECIAL io/quarkus/deployment/steps/BlockingOperationControlBuildStep$blockingOP15#<init>
    CHECKCAST io/quarkus/runtime/StartupTask
    ALOAD 0
    // Method descriptor: (Lio/quarkus/runtime/StartupContext;)V
    INVOKEINTERFACE io/quarkus/runtime/StartupTask#deploy
    NEW io/quarkus/deployment/steps/HttpSecurityProcessor$setupAuthenticationMechanisms14
    DUP
    // Method descriptor: ()V
    INVOKESPECIAL io/quarkus/deployment/steps/HttpSecurityProcessor$setupAuthenticationMechanisms14#<init>
    CHECKCAST io/quarkus/runtime/StartupTask
    ALOAD 0
    // Method descriptor: (Lio/quarkus/runtime/StartupContext;)V
    INVOKEINTERFACE io/quarkus/runtime/StartupTask#deploy
    NEW io/quarkus/deployment/steps/NettyProcessor$createExecutors6
    DUP
    // Method descriptor: ()V
    INVOKESPECIAL io/quarkus/deployment/steps/NettyProcessor$createExecutors6#<init>
    CHECKCAST io/quarkus/runtime/StartupTask
    ALOAD 0
    // Method descriptor: (Lio/quarkus/runtime/StartupContext;)V
    INVOKEINTERFACE io/quarkus/runtime/StartupTask#deploy
    NEW io/quarkus/deployment/steps/UndertowBuildStep$servletContextBean16
    DUP
    // Method descriptor: ()V
    INVOKESPECIAL io/quarkus/deployment/steps/UndertowBuildStep$servletContextBean16#<init>
    CHECKCAST io/quarkus/runtime/StartupTask
    ALOAD 0
    // Method descriptor: (Lio/quarkus/runtime/StartupContext;)V
    INVOKEINTERFACE io/quarkus/runtime/StartupTask#deploy
    NEW io/quarkus/deployment/steps/AgroalProcessor$build13
    DUP
    // Method descriptor: ()V
    INVOKESPECIAL io/quarkus/deployment/steps/AgroalProcessor$build13#<init>
    CHECKCAST io/quarkus/runtime/StartupTask
    ALOAD 0
    // Method descriptor: (Lio/quarkus/runtime/StartupContext;)V
    INVOKEINTERFACE io/quarkus/runtime/StartupTask#deploy
    NEW io/quarkus/deployment/steps/RuntimeBeanProcessor$build17
    DUP
    // Method descriptor: ()V
    INVOKESPECIAL io/quarkus/deployment/steps/RuntimeBeanProcessor$build17#<init>
    CHECKCAST io/quarkus/runtime/StartupTask
    ALOAD 0
    // Method descriptor: (Lio/quarkus/runtime/StartupContext;)V
    INVOKEINTERFACE io/quarkus/runtime/StartupTask#deploy
    NEW io/quarkus/deployment/steps/SubstrateConfigBuildStep$build18
    DUP
    // Method descriptor: ()V
    INVOKESPECIAL io/quarkus/deployment/steps/SubstrateConfigBuildStep$build18#<init>
    CHECKCAST io/quarkus/runtime/StartupTask
    ALOAD 0
    // Method descriptor: (Lio/quarkus/runtime/StartupContext;)V
    INVOKEINTERFACE io/quarkus/runtime/StartupTask#deploy
    NEW io/quarkus/deployment/steps/SubstrateSystemPropertiesBuildStep$writeNativeProps20
    DUP
    // Method descriptor: ()V
    INVOKESPECIAL io/quarkus/deployment/steps/SubstrateSystemPropertiesBuildStep$writeNativeProps20#<init>
    CHECKCAST io/quarkus/runtime/StartupTask
    ALOAD 0
    // Method descriptor: (Lio/quarkus/runtime/StartupContext;)V
    INVOKEINTERFACE io/quarkus/runtime/StartupTask#deploy
    NEW io/quarkus/deployment/steps/HibernateOrmProcessor$build19
    DUP
    // Method descriptor: ()V
    INVOKESPECIAL io/quarkus/deployment/steps/HibernateOrmProcessor$build19#<init>
    CHECKCAST io/quarkus/runtime/StartupTask
    ALOAD 0
    // Method descriptor: (Lio/quarkus/runtime/StartupContext;)V
    INVOKEINTERFACE io/quarkus/runtime/StartupTask#deploy
    NEW io/quarkus/deployment/steps/HibernateOrmProcessor$build21
    DUP
    // Method descriptor: ()V
    INVOKESPECIAL io/quarkus/deployment/steps/HibernateOrmProcessor$build21#<init>
    CHECKCAST io/quarkus/runtime/StartupTask
    ALOAD 0
    // Method descriptor: (Lio/quarkus/runtime/StartupContext;)V
    INVOKEINTERFACE io/quarkus/runtime/StartupTask#deploy
    NEW io/quarkus/deployment/steps/ArcProcessor$generateResources22
    DUP
    // Method descriptor: ()V
    INVOKESPECIAL io/quarkus/deployment/steps/ArcProcessor$generateResources22#<init>
    CHECKCAST io/quarkus/runtime/StartupTask
    ALOAD 0
    // Method descriptor: (Lio/quarkus/runtime/StartupContext;)V
    INVOKEINTERFACE io/quarkus/runtime/StartupTask#deploy
    NEW io/quarkus/deployment/steps/ResteasyCommonProcessor$setupResteasyInjection27
    DUP
    // Method descriptor: ()V
    INVOKESPECIAL io/quarkus/deployment/steps/ResteasyCommonProcessor$setupResteasyInjection27#<init>
    CHECKCAST io/quarkus/runtime/StartupTask
    ALOAD 0
    // Method descriptor: (Lio/quarkus/runtime/StartupContext;)V
    INVOKEINTERFACE io/quarkus/runtime/StartupTask#deploy
    NEW io/quarkus/deployment/steps/UndertowArcIntegrationBuildStep$integrateRequestContext25
    DUP
    // Method descriptor: ()V
    INVOKESPECIAL io/quarkus/deployment/steps/UndertowArcIntegrationBuildStep$integrateRequestContext25#<init>
    CHECKCAST io/quarkus/runtime/StartupTask
    ALOAD 0
    // Method descriptor: (Lio/quarkus/runtime/StartupContext;)V
    INVOKEINTERFACE io/quarkus/runtime/StartupTask#deploy
    NEW io/quarkus/deployment/steps/UndertowBuildStep$build32
    DUP
    // Method descriptor: ()V
    INVOKESPECIAL io/quarkus/deployment/steps/UndertowBuildStep$build32#<init>
    CHECKCAST io/quarkus/runtime/StartupTask
    ALOAD 0
    // Method descriptor: (Lio/quarkus/runtime/StartupContext;)V
    INVOKEINTERFACE io/quarkus/runtime/StartupTask#deploy
    RETURN
    ** label3
    GOTO label4
    ** label5
    ASTORE 1
    ALOAD 0
    // Method descriptor: ()V
    INVOKEVIRTUAL io/quarkus/runtime/StartupContext#close
    NEW java/lang/RuntimeException
    DUP
    LDC (String) "Failed to start quarkus"
    ALOAD 1
    // Method descriptor: (Ljava/lang/String;Ljava/lang/Throwable;)V
    INVOKESPECIAL java/lang/RuntimeException#<init>
    CHECKCAST java/lang/Throwable
    ATHROW
    ** label6
    GOTO label4
    // Try from label2 to label3
    // Catch java/lang/Throwable by going to label5
    ** label4
    ** label7
    
}

